torits_calculator/__init__.py
torits_calculator-0.0.1.dist-info/LICENSE.txt
torits_calculator-0.0.1.dist-info/METADATA
torits_calculator-0.0.1.dist-info/WHEEL
torits_calculator-0.0.1.dist-info/top_level.txt
torits_calculator-0.0.1.dist-info/RECORD
