Metadata-Version: 2.1
Name: torits-calculator
Version: 0.0.1
Summary: Two multipliers
Home-page: UNKNOWN
Author: Tor Inge Thorsen
Author-email: tor.i.thorsen@ntnu.no
License: MIT
Keywords: processing
Platform: UNKNOWN
Classifier: Programming Language :: Python :: 3
Classifier: Development Status :: 2 - Pre-Alpha
Classifier: License :: OSI Approved :: MIT License
Classifier: Intended Audience :: Education
Classifier: Operating System :: Microsoft :: Windows :: Windows 10
License-File: LICENSE.txt
